tadam/__init__.py
tadam/tadam.py
tadam-0.0.1.dist-info/LICENSE
tadam-0.0.1.dist-info/METADATA
tadam-0.0.1.dist-info/WHEEL
tadam-0.0.1.dist-info/top_level.txt
tadam-0.0.1.dist-info/RECORD
