Metadata-Version: 2.1
Name: tadam
Version: 0.0.1
Summary: TAdam optimizer for Pytorch
Home-page: https://github.com/kunzeng/tadam
Author: kun zeng
Author-email: zki@163.com
License: UNKNOWN
Platform: UNKNOWN
Classifier: Programming Language :: Python :: 3
Requires-Python: >=3.0
Requires-Dist: torch
